benchmark/__init__.py
benchmark/db_helper.py
benchmark/helper.py
benchmark/multiprocess_bm.py
benchmark/plot.py
benchmark/restore_dbs.py
benchmark/super_plot.py
benchmark/worker.py
benchmark/tests/__init__.py
benchmark/tests/test_argument_source_updates.py
benchmark/tests/test_duplicate_updates.py
benchmark/tests/test_multi_deps.py
benchmark/tests/test_nested_updates.py
benchmark/tests/test_relation_source_updates.py
example/__init__.py
example/app.py
example/test.py
example/worker.py
smache/__init__.py
smache/cache.py
smache/cache_manager.py
smache/cached_function_proxy.py
smache/computed_function.py
smache/computed_function_repository.py
smache/data_source_repository.py
smache/data_update_propagator.py
smache/dependency_graph_builder.py
smache/dsl.py
smache/function_serializer.py
smache/graph_drawer.py
smache/options.py
smache/relation_dependency_repository.py
smache/schedulers.py
smache/smache_logging.py
smache/testing.py
smache/timestamp_registry.py
smache/topological_sort.py
smache/data_sources/__init__.py
smache/data_sources/in_memory_data_source.py
smache/data_sources/mongo_data_source.py
smache/data_sources/raw_data_source.py
smache/dependency_graphs/__init__.py
smache/dependency_graphs/redis_dependency_graph.py
smache/stores/__init__.py
smache/stores/cache_result.py
smache/stores/redis_store.py
smache-0.0.9.data/scripts/smache
smache-0.0.9.dist-info/DESCRIPTION.rst
smache-0.0.9.dist-info/METADATA
smache-0.0.9.dist-info/RECORD
smache-0.0.9.dist-info/WHEEL
smache-0.0.9.dist-info/metadata.json
smache-0.0.9.dist-info/top_level.txt
tests/integration/__init__.py
tests/integration/test_computed_function.py
tests/integration/test_drawing.py
tests/integration/test_function_serialization.py
tests/integration/test_mongo_source.py
tests/integration/test_relations.py
tests/integration/test_smache.py
tests/integration/test_testing_utilities.py
tests/integration/test_ttl.py
tests/integration/test_write_through.py
