Metadata-Version: 2.0
Name: smache
Version: 0.0.9
Summary: 
Requires-Dist: redis (==2.10)
Requires-Dist: blinker (==1.4)
Requires-Dist: mongoengine (<0.11,>=0.10.6)
Requires-Dist: rq (==0.5.6)
Requires-Dist: dagger (==1.3.0)
Requires-Dist: docopt (<0.7.0,>=0.6.0)
